mw75_streamer/__init__.py
mw75_streamer/__main__.py
mw75_streamer/config.py
mw75_streamer/main.py
mw75_streamer/assets/mw75.webp
mw75_streamer/data/__init__.py
mw75_streamer/data/packet_processor.py
mw75_streamer/data/streamers.py
mw75_streamer/device/__init__.py
mw75_streamer/device/ble_manager.py
mw75_streamer/device/mw75_device.py
mw75_streamer/device/rfcomm_manager.py
mw75_streamer/panel/__init__.py
mw75_streamer/panel/panel.html
mw75_streamer/panel/panel_server.py
mw75_streamer/server/__init__.py
mw75_streamer/server/__main__.py
mw75_streamer/server/ws_server.py
mw75_streamer/testing/__init__.py
mw75_streamer/testing/__main__.py
mw75_streamer/testing/eeg_test_client.html
mw75_streamer/testing/test_guide.py
mw75_streamer/testing/websocket_server.py
mw75_streamer/utils/__init__.py
mw75_streamer/utils/logging.py
mw75_streamer-1.0.8.dist-info/licenses/LICENSE
mw75_streamer-1.0.8.dist-info/METADATA
mw75_streamer-1.0.8.dist-info/WHEEL
mw75_streamer-1.0.8.dist-info/entry_points.txt
mw75_streamer-1.0.8.dist-info/top_level.txt
mw75_streamer-1.0.8.dist-info/RECORD
