Metadata-Version: 2.4
Name: mw75-streamer
Version: 1.0.8
Summary: Stream EEG data from MW75 Neuro headphones using BLE and RFCOMM
Author-email: Eitan Kay <opensource@arctop.com>
Maintainer-email: Arctop <opensource@arctop.com>
License-Expression: MIT
Project-URL: Homepage, https://github.com/arctop/mw75-streamer
Project-URL: Documentation, https://arctop.github.io/mw75-streamer/api/
Project-URL: Repository, https://github.com/arctop/mw75-streamer
Project-URL: Bug Tracker, https://github.com/arctop/mw75-streamer/issues
Project-URL: Company, https://arctop.com
Keywords: eeg,mw75,neurotechnology,bluetooth,streaming,arctop
Classifier: Development Status :: 4 - Beta
Classifier: Intended Audience :: Science/Research
Classifier: Operating System :: MacOS :: MacOS X
Classifier: Programming Language :: Python :: 3
Classifier: Programming Language :: Python :: 3.9
Classifier: Programming Language :: Python :: 3.10
Classifier: Programming Language :: Python :: 3.11
Classifier: Programming Language :: Python :: 3.12
Classifier: Topic :: Scientific/Engineering :: Medical Science Apps.
Classifier: Topic :: System :: Hardware :: Hardware Drivers
Requires-Python: >=3.9
License-File: LICENSE
Requires-Dist: bleak>=0.20.0
Requires-Dist: pyobjc>=9.0; sys_platform == "darwin"
Requires-Dist: pyobjc-framework-IOBluetooth>=9.0; sys_platform == "darwin"
Provides-Extra: websocket
Requires-Dist: websocket-client>=1.6.0; extra == "websocket"
Provides-Extra: lsl
Requires-Dist: pylsl>=1.16.0; extra == "lsl"
Provides-Extra: testing
Requires-Dist: websockets>=11.0.0; extra == "testing"
Provides-Extra: docs
Requires-Dist: sphinx>=7.0.0; extra == "docs"
Requires-Dist: sphinx-rtd-theme>=2.0.0; extra == "docs"
Requires-Dist: sphinx-autodoc-typehints>=1.25.0; extra == "docs"
Requires-Dist: myst-parser>=2.0.0; extra == "docs"
Provides-Extra: dev
Requires-Dist: pytest>=7.0.0; extra == "dev"
Requires-Dist: black>=23.0.0; extra == "dev"
Requires-Dist: flake8>=6.0.0; extra == "dev"
Requires-Dist: mypy>=1.0.0; extra == "dev"
Requires-Dist: websocket-client>=1.6.0; extra == "dev"
Requires-Dist: websockets>=11.0.0; extra == "dev"
Requires-Dist: pylsl>=1.16.0; extra == "dev"
Requires-Dist: sphinx>=7.0.0; extra == "dev"
Requires-Dist: sphinx-rtd-theme>=2.0.0; extra == "dev"
Requires-Dist: sphinx-autodoc-typehints>=1.25.0; extra == "dev"
Requires-Dist: myst-parser>=2.0.0; extra == "dev"
Provides-Extra: all
Requires-Dist: websocket-client>=1.6.0; extra == "all"
Requires-Dist: websockets>=11.0.0; extra == "all"
Requires-Dist: pylsl>=1.16.0; extra == "all"
Dynamic: license-file
